gobstopper-0.2.7.dist-info/METADATA
gobstopper-0.2.7.dist-info/WHEEL
gobstopper-0.2.7.dist-info/entry_points.txt
gobstopper/__init__.py
gobstopper/_core.cpython-313-aarch64-linux-gnu.so
gobstopper/cli/__init__.py
gobstopper/cli/main.py
gobstopper/cli/template_engine.py
gobstopper/cli/templates/blueprints_app.py.j2
gobstopper/cli/templates/blueprints_auth.py.j2
gobstopper/cli/templates/blueprints_init.py.j2
gobstopper/cli/templates/cms_app.py.j2
gobstopper/cli/templates/cms_env.j2
gobstopper/cli/templates/cms_readme.md.j2
gobstopper/cli/templates/cms_requirements.txt.j2
gobstopper/cli/templates/content_models.py.j2
gobstopper/cli/templates/dashboard_app.py.j2
gobstopper/cli/templates/dashboard_env.j2
gobstopper/cli/templates/dashboard_readme.md.j2
gobstopper/cli/templates/data_science_app.py.j2
gobstopper/cli/templates/data_science_env.j2
gobstopper/cli/templates/data_science_readme.md.j2
gobstopper/cli/templates/microservice_app.py.j2
gobstopper/cli/templates/microservice_readme.md.j2
gobstopper/cli/templates/microservice_requirements.txt.j2
gobstopper/cli/templates/microservices_app.py.j2
gobstopper/cli/templates/ml_models.py.j2
gobstopper/cli/templates/modular_app.py.j2
gobstopper/cli/templates/modules_init.py.j2
gobstopper/cli/templates/single_app.py.j2
gobstopper/config.py
gobstopper/core/__init__.py
gobstopper/core/app.py
gobstopper/core/blueprint.py
gobstopper/extensions/__init__.py
gobstopper/extensions/charts/__init__.py
gobstopper/extensions/charts/builders.py
gobstopper/extensions/charts/extension.py
gobstopper/extensions/charts/filters.py
gobstopper/extensions/charts/streaming.py
gobstopper/extensions/charts/themes.py
gobstopper/extensions/charts/types.py
gobstopper/extensions/openapi/__init__.py
gobstopper/extensions/openapi/adapters_dataclasses.py
gobstopper/extensions/openapi/adapters_msgspec.py
gobstopper/extensions/openapi/adapters_typeddict.py
gobstopper/extensions/openapi/decorators.py
gobstopper/extensions/openapi/generator.py
gobstopper/extensions/openapi/typing_adapters.py
gobstopper/extensions/openapi/ui.py
gobstopper/http/__init__.py
gobstopper-0.2.7.dist-info/RECORD
