Metadata-Version: 2.4
Name: gobstopper
Version: 0.2.7
Classifier: Development Status :: 3 - Alpha
Classifier: Environment :: Web Environment
Classifier: Framework :: AsyncIO
Classifier: Intended Audience :: Developers
Classifier: License :: OSI Approved :: MIT License
Classifier: Operating System :: OS Independent
Classifier: Programming Language :: Python :: 3
Classifier: Programming Language :: Python :: 3.10
Classifier: Programming Language :: Python :: 3.11
Classifier: Programming Language :: Python :: 3.12
Classifier: Programming Language :: Python :: 3.13
Classifier: Topic :: Internet :: WWW/HTTP :: Dynamic Content
Classifier: Topic :: Software Development :: Libraries :: Python Modules
Requires-Dist: aiohttp==3.13.0
Requires-Dist: granian[reload]==2.5.5
Requires-Dist: loguru>=0.7.2
Requires-Dist: msgspec
Requires-Dist: uvloop
Requires-Dist: typing-extensions==4.15.0
Requires-Dist: anyio==4.11.0
Requires-Dist: jinja2>=3.1.0 ; extra == 'templates'
Requires-Dist: duckdb>=0.9.0 ; extra == 'tasks'
Requires-Dist: click>=8.0.0 ; extra == 'cli'
Requires-Dist: redis>=5.0 ; extra == 'redis'
Requires-Dist: asyncpg ; extra == 'postgres'
Requires-Dist: pyecharts>=2.0.0 ; extra == 'charts'
Requires-Dist: pytest>=7.0.0 ; extra == 'dev'
Requires-Dist: pytest-asyncio>=0.21.0 ; extra == 'dev'
Requires-Dist: black>=23.0.0 ; extra == 'dev'
Requires-Dist: ruff>=0.1.0 ; extra == 'dev'
Requires-Dist: mypy>=1.0.0 ; extra == 'dev'
Requires-Dist: httpx>=0.24.1 ; extra == 'dev'
Requires-Dist: duckdb>=0.9.0 ; extra == 'dev'
Requires-Dist: maturin>=1.0.0 ; extra == 'dev'
Requires-Dist: jinja2>=3.1.0 ; extra == 'all'
Requires-Dist: duckdb>=0.9.0 ; extra == 'all'
Requires-Dist: click>=8.0.0 ; extra == 'all'
Requires-Dist: pyecharts>=2.0.0 ; extra == 'all'
Provides-Extra: templates
Provides-Extra: tasks
Provides-Extra: cli
Provides-Extra: redis
Provides-Extra: postgres
Provides-Extra: charts
Provides-Extra: dev
Provides-Extra: all
Summary: A simple wrapper delivering complete web framework power - like Wonka's Gobstopper, wrapping RSGI complexity into Flask-like simplicity
Keywords: web,framework,async,rsgi,granian,background-tasks
Author: Gobstopper Framework Team
License: MIT
Requires-Python: >=3.10
Project-URL: Homepage, https://github.com/iristech-systems/gobstopper
Project-URL: Documentation, https://iristech-systems.github.io/Gobstopper-Docs/
Project-URL: Repository, https://github.com/iristech-systems/gobstopper
Project-URL: Issues, https://github.com/iristech-systems/gobstopper/issues
